ropt_eo/__init__.py
ropt_eo/everest_optimizers.py
ropt_eo/py.typed
ropt_eo/version.py
ropt_eo-0.1.0.dist-info/licenses/LICENSE
ropt_eo-0.1.0.dist-info/METADATA
ropt_eo-0.1.0.dist-info/WHEEL
ropt_eo-0.1.0.dist-info/entry_points.txt
ropt_eo-0.1.0.dist-info/top_level.txt
ropt_eo-0.1.0.dist-info/RECORD
